logtos3/__init__.py
logtos3/upload.py
logtos3-0.0.19.dist-info/METADATA
logtos3-0.0.19.dist-info/WHEEL
logtos3-0.0.19.dist-info/top_level.txt
logtos3-0.0.19.dist-info/RECORD
